auto_identify/__init__.py
auto_identify/__main__.py
auto_identify/k.py
auto_identify-0.1.2.dist-info/METADATA
auto_identify-0.1.2.dist-info/WHEEL
auto_identify-0.1.2.dist-info/entry_points.txt
auto_identify-0.1.2.dist-info/RECORD
