Metadata-Version: 2.3
Name: auto_identify
Version: 0.1.2
Summary: Add your description here
Author-email: todo <todo@todo.todo>
Requires-Python: >=3.10
Requires-Dist: autonomous-proto>=0.1.4
Requires-Dist: matplotlib>=3.10.3
Requires-Dist: pyside6>=6.9.1
Requires-Dist: rosbags>=0.10.10
Requires-Dist: scipy>=1.15.3
Requires-Dist: typer>=0.16.0
